.travis.yml
LICENSE
MANIFEST.in
README.rst
requirements.txt
setup.cfg
setup.py
pg2kinesis/__init__.py
pg2kinesis/__main__.py
pg2kinesis/formatter.py
pg2kinesis/log.py
pg2kinesis/slot.py
pg2kinesis/stream.py
pg2kinesis.egg-info/PKG-INFO
pg2kinesis.egg-info/SOURCES.txt
pg2kinesis.egg-info/dependency_links.txt
pg2kinesis.egg-info/entry_points.txt
pg2kinesis.egg-info/requires.txt
pg2kinesis.egg-info/top_level.txt
pg2kinesis.egg-info/zip-safe
tests/__init__.py
tests/test___main__.py
tests/test_formatter.py
tests/test_slot.py
tests/test_stream.py