Metadata-Version: 1.2
Name: pg2kinesis
Version: 0.7.0
Summary: A utility that enables PostgreSQL 9.4+ to logically replicate to Amazon
Home-page: https://github.com/handshake/pg2kinesis
Author: Shon T. Urbas, Geoff Johnson
Author-email: shon.urbas@gmail.com, geoff.johnson@handshake.com
Maintainer: Shon T. Urbas, Geoff Johnson
Maintainer-email: shon.urbas@gmail.com, geoff.johnson@handshake.com
License: MIT
Keywords: logical replication,kinesis,database
Platform: UNKNOWN
Classifier: Development Status :: 5 - Production/Stable
Classifier: Intended Audience :: Developers
Classifier: Natural Language :: English
Classifier: License :: OSI Approved :: MIT License
Classifier: Operating System :: OS Independent
Classifier: Programming Language :: Python
Classifier: Programming Language :: Python :: 2
Classifier: Programming Language :: Python :: 2.7
Classifier: Programming Language :: Python :: 3
Classifier: Programming Language :: Python :: 3.3
Classifier: Programming Language :: Python :: 3.4
Classifier: Programming Language :: Python :: 3.5
Classifier: Programming Language :: Python :: 3.6
Classifier: Programming Language :: Python :: Implementation :: CPython
Classifier: Topic :: Utilities
